torippy/__init__.py
torippy/gui/__init__.py
torippy/gui/keycode.py
torippy/main.py
torippy-0.1.4.dist-info/METADATA
torippy-0.1.4.dist-info/WHEEL
torippy-0.1.4.dist-info/RECORD
