Metadata-Version: 2.1
Name: torippy
Version: 0.1.4
Summary: 
Author: torippy
Author-email: 47879788+torippy1024@users.noreply.github.com
Requires-Python: >=3.10,<3.12
Classifier: Programming Language :: Python :: 3
Classifier: Programming Language :: Python :: 3.10
Classifier: Programming Language :: Python :: 3.11
Requires-Dist: pillow (>=9.4.0,<10.0.0)
Requires-Dist: pyautogui (>=0.9.53,<0.10.0)
